MISOReports/MISOReports.py
MISOReports/__init__.py
MISOReports/parsers.py
_scripts/__init__.py
_scripts/tmp.py
MISOReports-0.0.0.dist-info/LICENSE
MISOReports-0.0.0.dist-info/METADATA
MISOReports-0.0.0.dist-info/WHEEL
MISOReports-0.0.0.dist-info/top_level.txt
MISOReports-0.0.0.dist-info/RECORD
