Metadata-Version: 2.1
Name: MISOReports
Version: 0.0.0
Summary: A comprehensive Python library for downloading Midcontinent Independent System Operator (MISO) public reports into pandas dataframes.
Home-page: https://github.com/BrianWeiHaoMa/MISOReports
Author: Brian Wei Hao Ma, Ryan B. Green, William Sun
Author-email: brianmaytc@gmail.com
License: MIT
Keywords: python,data-science,scraper,download,pandas,reports,electricity,tables,data-tables,data-scraping,miso,energy-markets,electricity-markets
Classifier: Development Status :: 4 - Beta
Classifier: License :: OSI Approved :: MIT License
Classifier: Intended Audience :: Developers
Classifier: Intended Audience :: Science/Research
Classifier: Intended Audience :: Information Technology
Classifier: Operating System :: OS Independent
Classifier: Topic :: Software Development :: Libraries
Classifier: Topic :: Utilities
Classifier: Programming Language :: Python :: 3.10
Classifier: Programming Language :: Python :: 3.11
Classifier: Programming Language :: Python :: 3.12
Classifier: Programming Language :: Python :: 3.13
Requires-Python: >=3.10
License-File: LICENSE
Requires-Dist: pandas<3.0.0,>=2.2.0
Requires-Dist: requests<3.0.0,>=2.32.0
